Region_RNE/__init__.py
Region_RNE/main.py
Region_RNE-0.0.1.dist-info/LICENSE
Region_RNE-0.0.1.dist-info/METADATA
Region_RNE-0.0.1.dist-info/WHEEL
Region_RNE-0.0.1.dist-info/top_level.txt
Region_RNE-0.0.1.dist-info/RECORD
