Metadata-Version: 2.1
Name: Region-RNE
Version: 0.0.1
Summary: A Python package to fetch and print Dataframe for Region RNE data.
Author-email: Hossam Ibrahim <hossam.ibrahim@hlag.com>
License: Copyright (c) [2023] [Hossam_Ibrahim]
License-File: LICENSE
Requires-Dist: requests
Requires-Dist: pandas
